setup.py
bin/blackhole
bin/blackhole.bat
tcp_blackhole/__init__.py
tcp_blackhole/tcp_blackhole.py
tcp_blackhole.egg-info/PKG-INFO
tcp_blackhole.egg-info/SOURCES.txt
tcp_blackhole.egg-info/dependency_links.txt
tcp_blackhole.egg-info/not-zip-safe
tcp_blackhole.egg-info/requires.txt
tcp_blackhole.egg-info/top_level.txt