Metadata-Version: 1.0
Name: tcp-blackhole
Version: 0.3.3
Summary: TCP Blackhole is a server that can discard data it receives, print it to standard out, or echo it back to the client as raw data or as an HTTP 200 OK response.
Home-page: https://github.com/NanoDano/tcp_blackhole
Author: NanoDano
Author-email: nanodano@devdungeon.com
License: MIT
Platform: UNKNOWN
